nxbench/__init__.py
nxbench/_version.py
nxbench/cli.py
nxbench/log.py
nxbench/backends/__init__.py
nxbench/backends/core.py
nxbench/backends/registry.py
nxbench/benchmarking/__init__.py
nxbench/benchmarking/benchmark.py
nxbench/benchmarking/config.py
nxbench/benchmarking/constants.py
nxbench/benchmarking/export.py
nxbench/benchmarking/utils.py
nxbench/configs/__init__.py
nxbench/configs/example.yaml
nxbench/data/__init__.py
nxbench/data/constants.py
nxbench/data/db.py
nxbench/data/loader.py
nxbench/data/network_directory.csv
nxbench/data/repository.py
nxbench/data/synthesize.py
nxbench/data/utils.py
nxbench/validation/__init__.py
nxbench/validation/base.py
nxbench/validation/registry.py
nxbench/viz/__init__.py
nxbench/viz/app.py
nxbench/viz/utils.py
nxbench-0.1.24.dist-info/LICENSE
nxbench-0.1.24.dist-info/METADATA
nxbench-0.1.24.dist-info/WHEEL
nxbench-0.1.24.dist-info/entry_points.txt
nxbench-0.1.24.dist-info/top_level.txt
nxbench-0.1.24.dist-info/RECORD
