Metadata-Version: 2.1
Name: nxbench
Version: 0.1.24
Summary: A centralized benchmarking suite to facilitate comparative profiling of tools across graph analytic libraries and datasets
Author-email: Derek Alexander <dpysalexander@gmail.com>
Keywords: networkx,graph,network,benchmarking,profiling
Classifier: Intended Audience :: Developers
Classifier: Intended Audience :: Science/Research
Classifier: Operating System :: OS Independent
Classifier: Programming Language :: Python :: 3
Classifier: Programming Language :: Python :: 3.10
Classifier: Programming Language :: Python :: 3.11
Classifier: Programming Language :: Python :: 3.12
Classifier: Programming Language :: Python :: 3 :: Only
Requires-Python: >=3.10
License-File: LICENSE
Requires-Dist: numpy>=1.26
Requires-Dist: scipy>=1.14.1
Requires-Dist: networkx>=3.3
Requires-Dist: psutil>=5.9
Requires-Dist: pandas>=2.2.2
Requires-Dist: pydantic>=2.8
Requires-Dist: setuptools>=75.1
Requires-Dist: nest-asyncio>=1.6
Requires-Dist: dash>=2.18.1
Requires-Dist: dash-bootstrap-components>=1.6.0
Requires-Dist: aiohttp>=3.9.5
Requires-Dist: aiofiles>=24.1.0
Requires-Dist: chardet>=4.0.0
Requires-Dist: beautifulsoup4>=4.12.3
Requires-Dist: multidict>=6.0.5
Requires-Dist: yarl>=1.9.4
Requires-Dist: dask>=2024.12.1
Requires-Dist: distributed>=2024.12.1
Requires-Dist: prefect>=3.1.8
Requires-Dist: prefect_dask>=0.3.2
Requires-Dist: bokeh>=3.1.0
Requires-Dist: asyncpg>=0.30.0
Requires-Dist: lxml>=5.2.1
Provides-Extra: test
Requires-Dist: pre-commit>=3.8.0; extra == "test"
Requires-Dist: pre-commit-hooks>=5.0.0; extra == "test"
Requires-Dist: black>=22.6.0; extra == "test"
Requires-Dist: ruff>=0.6.9; extra == "test"
Requires-Dist: pytest-sugar>=0.9.3; extra == "test"
Requires-Dist: pytest>=7.2; extra == "test"
Requires-Dist: pytest-cov>=2.7.1; extra == "test"
Requires-Dist: pytest-split>=0.7.0; extra == "test"
Requires-Dist: pytest-xdist>=1.32.0; extra == "test"
Requires-Dist: pytest-metadata>=2.0.2; extra == "test"
Requires-Dist: pytest-env>=1.1.5; extra == "test"
Requires-Dist: pytest-asyncio>=0.24.0; extra == "test"
Requires-Dist: coverage>=7.6.1; extra == "test"
Requires-Dist: build>=1.2.2; extra == "test"
Requires-Dist: isort>=5.13.2; extra == "test"
Provides-Extra: doc
Requires-Dist: setuptools>=45.0.0; extra == "doc"
Requires-Dist: pydata-sphinx-theme==0.15.4; extra == "doc"
Requires-Dist: furo==2024.8.6; extra == "doc"
Requires-Dist: sphinxcontrib-apidoc~=0.3.0; extra == "doc"
Requires-Dist: sphinx-autobuild==2024.10.3; extra == "doc"
Requires-Dist: sphinxcontrib-napoleon; extra == "doc"
Requires-Dist: myst_parser>=4.0.0; extra == "doc"
Requires-Dist: sphinx_autodoc_typehints>=2.4.4; extra == "doc"
Requires-Dist: sphinx<9.0.0,>=8.0.2; extra == "doc"
